pepid/__init__.py
pepid/__main__.py
pepid/blackboard.py
pepid/db.py
pepid/db_node.py
pepid/drop_columns.py
pepid/drop_node.py
pepid/example_proteometools.cfg
pepid/example_proteometools_ml.cfg
pepid/example_yeast.cfg
pepid/extensions.py
pepid/finetune_rf_rescorer.py
pepid/gen_fdp_report.py
pepid/gen_fdp_report_debug.py
pepid/gen_fdr_report.py
pepid/main.py
pepid/node.py
pepid/output_node.py
pepid/pepid_compare.py
pepid/pepid_files.py
pepid/pepid_io.py
pepid/pepid_mgf_meta.py
pepid/pepid_mp.py
pepid/pepid_percolator.py
pepid/pepid_postprocess.py
pepid/pepid_randomforest.py
pepid/pepid_rescore.py
pepid/pepid_search.py
pepid/pepid_utils.py
pepid/pin_node.py
pepid/post_node.py
pepid/queries.py
pepid/queries_node.py
pepid/scratch.py
pepid/search.py
pepid/search_node.py
pepid/test_model.py
pepid/test_specgen.py
pepid/data/default.cfg
pepid/ml/__init__.py
pepid/ml/best_lgt_model.py
pepid/ml/specgen.py
pepid/ml/train_best_lgt_model.py
pepid/ml/train_rf_rescorer.py
pepid/ml/train_specgen.py
pepid-1.2.0.dist-info/METADATA
pepid-1.2.0.dist-info/WHEEL
pepid-1.2.0.dist-info/licenses/LICENSE.md
pepid-1.2.0.dist-info/RECORD
