Metadata-Version: 2.1
Name: pepid
Version: 1.2.0
Summary: Pepid: a Highly Modifiable, Bioinformatics-Oriented Peptide Search Engine
Project-URL: Homepage, https://github.com/lemieux-lab/pepid
Project-URL: Bug Tracker, https://github.com/lemieux-lab/pepid/issues
Author-email: Jeremie Zumer <jeremie.zumer@umontreal.ca>
License-File: LICENSE.md
Classifier: Development Status :: 5 - Production/Stable
Classifier: Intended Audience :: Developers
Classifier: Intended Audience :: Healthcare Industry
Classifier: Intended Audience :: Science/Research
Classifier: License :: OSI Approved :: MIT License
Classifier: Operating System :: POSIX :: Linux
Classifier: Topic :: Scientific/Engineering :: Bio-Informatics
Requires-Python: >=3.7
